quantmod/__init__.py
quantmod/_version.py
quantmod/main.py
quantmod/utils.py
quantmod/version.py
quantmod/charts/__init__.py
quantmod/charts/plotting.py
quantmod/charts/themes.py
quantmod/datasets/__init__.py
quantmod/datasets/dataloader.py
quantmod/datasets/data/__init__.py
quantmod/datasets/data/nifty50.csv
quantmod/datasets/data/spx.csv
quantmod/db/__init__.py
quantmod/db/database.py
quantmod/derivatives/__init__.py
quantmod/derivatives/nse.py
quantmod/derivatives/optionchain.py
quantmod/derivatives/options.py
quantmod/indicators/__init__.py
quantmod/indicators/indicators.py
quantmod/markets/__init__.py
quantmod/markets/bb.py
quantmod/markets/yahoo.py
quantmod/models/__init__.py
quantmod/models/binomial.py
quantmod/models/blackscholes.py
quantmod/models/montecarlo.py
quantmod/models/optioninputs.py
quantmod/risk/__init__.py
quantmod/risk/riskinputs.py
quantmod/risk/var.py
quantmod/risk/varbacktest.py
quantmod/risk/varbacktester.py
quantmod/risk/varinputs.py
quantmod/timeseries/__init__.py
quantmod/timeseries/performance.py
quantmod/timeseries/timeseries.py
quantmod-0.1.3.dist-info/LICENSE.txt
quantmod-0.1.3.dist-info/METADATA
quantmod-0.1.3.dist-info/WHEEL
quantmod-0.1.3.dist-info/entry_points.txt
quantmod-0.1.3.dist-info/top_level.txt
quantmod-0.1.3.dist-info/RECORD
