Metadata-Version: 2.2
Name: quantmod
Version: 0.1.3
Summary: Quantmod Python Package
Home-page: https://kannansingaravelu.com/
Author: Kannan Singaravelu
Author-email: inquant@outlook.com
License: Apache License 2.0
Keywords: python,quant,quantmod,quantmod-python
Platform: any
Classifier: License :: OSI Approved :: Apache Software License
Classifier: Programming Language :: Python :: 3.10
Classifier: Operating System :: OS Independent
Classifier: Intended Audience :: Developers
Classifier: Topic :: Office/Business :: Financial
Classifier: Topic :: Office/Business :: Financial :: Investment
Classifier: Topic :: Software Development :: Libraries
Classifier: Topic :: Software Development :: Libraries :: Python Modules
Requires-Python: >=3.10
License-File: LICENSE.txt
Requires-Dist: joblib
Requires-Dist: matplotlib
Requires-Dist: nbformat>=5.10.4
Requires-Dist: numpy>=2.0.2
Requires-Dist: pandas>=2.2.2
Requires-Dist: plotly>=6.1.2
Requires-Dist: pydantic>=2.8.2
Requires-Dist: scipy>=1.13.1
Requires-Dist: sqlalchemy>=2.0.38
Requires-Dist: supabase>=2.27.2
Requires-Dist: tabulate>=0.9.0
Requires-Dist: urllib3==1.26.15
Requires-Dist: yfinance>=1.0
Dynamic: author
Dynamic: author-email
Dynamic: classifier
Dynamic: description
Dynamic: description-content-type
Dynamic: home-page
Dynamic: keywords
Dynamic: license
Dynamic: platform
Dynamic: requires-dist
Dynamic: requires-python
Dynamic: summary
